{
    "market_type": "futures",
    "user": "bybit_pro",
    "symbol": "AVAXUSDT",
    "latency_simulation_ms": 1000,
    "starting_balance": 1000.0,
    "start_date": "2021-01-01",
    "end_date": "2022-07-23",
    "base_dir": "/home/tedy/passivbot5.4.2tedy/configs/live/PBSO/BT_UNIFORMISED/strat_6f8a4/",
    "ohlcv": true,
    "spot": false,
    "exchange": "bybit",
    "session_name": "2021-01-01_2022-07-23",
    "caches_dirpath": "/home/tedy/passivbot5.4.2tedy/configs/live/PBSO/BT_UNIFORMISED/strat_6f8a4/bybit/AVAXUSDT/caches/",
    "optimize_dirpath": "/home/tedy/passivbot5.4.2tedy/configs/live/PBSO/BT_UNIFORMISED/strat_6f8a4/bybit/AVAXUSDT/optimize/",
    "plots_dirpath": "/home/tedy/passivbot5.4.2tedy/configs/live/PBSO/BT_UNIFORMISED/strat_6f8a4/bybit/AVAXUSDT/plots/2022-07-31T091541/",
    "maker_fee": 0.0001,
    "taker_fee": 0.0006,
    "inverse": false,
    "max_leverage": 50,
    "min_qty": 0.1,
    "min_cost": 0.0,
    "qty_step": 0.1,
    "price_step": 0.005,
    "c_mult": 1.0,
    "hedge_mode": true,
    "n_parts": 0,
    "config_name": "neat_grid_0days",
    "logging_level": 0,
    "long": {
        "auto_unstuck_ema_dist": 0,
        "auto_unstuck_wallet_exposure_threshold": 0,
        "backwards_tp": true,
        "ema_span_0": 75.48466964495677,
        "ema_span_1": 10,
        "enabled": true,
        "eprice_exp_base": 1.0029839299239351,
        "eqty_exp_base": 1.5463815615643637,
        "grid_span": 0.28073986391272665,
        "initial_eprice_ema_dist": -0.06148581145293449,
        "initial_qty_pct": 0.013061235557801245,
        "markup_range": 0.01561149675022753,
        "max_n_entry_orders": 8,
        "min_markup": 0.002,
        "n_close_orders": 9,
        "wallet_exposure_limit": 0.9090909090909091
    },
    "short": {
        "auto_unstuck_ema_dist": 0,
        "auto_unstuck_wallet_exposure_threshold": 0,
        "backwards_tp": true,
        "ema_span_0": 3658.6292128210684,
        "ema_span_1": 2966.953016757011,
        "enabled": true,
        "eprice_exp_base": 1.002196554870229,
        "eqty_exp_base": 2.699920584610612,
        "grid_span": 0.2385568895428234,
        "initial_eprice_ema_dist": -0.0033974063494721348,
        "initial_qty_pct": 0.011392682878266806,
        "markup_range": 0,
        "max_n_entry_orders": 16,
        "min_markup": 0.00981878494695824,
        "n_close_orders": 19,
        "wallet_exposure_limit": 0.09090909090909091
    },
    "n_days": 568.0,
    "passivbot_mode": "neat_grid",
    "result": {
        "DGstd_long": 0.03831839219824906,
        "DGstd_short": 0.018905236801402436,
        "adg_DGstd_ratio_long": 0.037092666674947684,
        "adg_DGstd_ratio_short": 0.01349445921910315,
        "adg_long": 0.0014213313493295684,
        "adg_per_exposure_long": 0.0015634644842625253,
        "adg_per_exposure_short": 0.0028062754174841453,
        "adg_realized_long": 0.001936579093284596,
        "adg_realized_per_exposure_long": 0.0021302370026130557,
        "adg_realized_per_exposure_short": 0.0008383600523711454,
        "adg_realized_short": 7.621455021555867e-05,
        "adg_short": 0.00025511594704401324,
        "avg_fills_per_day_long": 8.96833178876122,
        "avg_fills_per_day_short": 3.533459344335251,
        "biggest_psize_long": 68.3,
        "biggest_psize_quote_long": 2722.8469999999998,
        "biggest_psize_quote_short": 95.55300000000001,
        "biggest_psize_short": 21.3,
        "closest_bkr_long": 1.0,
        "closest_bkr_short": 1.0,
        "eqbal_ratio_mean_long": 0.854845435811811,
        "eqbal_ratio_mean_short": 0.9006123167093966,
        "eqbal_ratio_min_long": 0.32353943499390125,
        "eqbal_ratio_min_short": 0.5671958228026904,
        "equity_balance_ratio_mean_long": 0.854845435811811,
        "equity_balance_ratio_mean_short": 0.9006123167093966,
        "equity_balance_ratio_std_long": 0.22879753765082042,
        "equity_balance_ratio_std_short": 0.1003180275750218,
        "exchange": "bybit",
        "fee_sum_long": -26.044878073,
        "fee_sum_short": -0.719723813,
        "final_balance_long": 3000.8948119269867,
        "final_balance_short": 1044.2387061870004,
        "final_equity_long": 1470.352811926987,
        "final_equity_short": 1044.2387061870004,
        "gain_long": 2.0269396899999985,
        "gain_short": 0.044958430000000195,
        "hrs_stuck_avg": 6.870950940860215,
        "hrs_stuck_avg_long": 2.7522646207685577,
        "hrs_stuck_avg_short": 6.870950940860215,
        "hrs_stuck_max": 6398.2,
        "hrs_stuck_max_long": 2195.766666666667,
        "hrs_stuck_max_short": 6398.2,
        "loss_sum_long": 0.0,
        "loss_sum_short": 0.0,
        "n_closes_long": 2162,
        "n_closes_short": 548,
        "n_days": 567.9986111111111,
        "n_entries_long": 2932,
        "n_entries_short": 1459,
        "n_fills_long": 5094,
        "n_fills_short": 2007,
        "n_ientries_long": 1872,
        "n_ientries_short": 548,
        "n_normal_closes_long": 2162,
        "n_normal_closes_short": 548,
        "n_rentries_long": 1060,
        "n_rentries_short": 911,
        "n_unstuck_closes_long": 0,
        "n_unstuck_closes_short": 0,
        "n_unstuck_entries_long": 0,
        "n_unstuck_entries_short": 0,
        "net_pnl_plus_fees_long": 2000.8948119269983,
        "net_pnl_plus_fees_short": 44.23870618700019,
        "pa_distance_max_long": 2.9298660624079895,
        "pa_distance_max_short": 0.8237238676441744,
        "pa_distance_mean_long": 0.39669446485950427,
        "pa_distance_mean_short": 0.44499064304666913,
        "pa_distance_std_long": 0.6575340473322231,
        "pa_distance_std_short": 0.2683411878510533,
        "pnl_sum_long": 2026.9396899999983,
        "pnl_sum_short": 44.95843000000019,
        "profit_sum_long": 2026.9396899999983,
        "profit_sum_short": 44.9584300000002,
        "starting_balance": 1000.0,
        "symbol": "AVAXUSDT",
        "volume_quote_long": 260448.78073,
        "volume_quote_short": 7197.23813
    }
}