{
    "market_type": "futures",
    "user": "bybit_pro",
    "symbol": "AVAXUSDT",
    "latency_simulation_ms": 1000,
    "starting_balance": 1000.0,
    "start_date": "2021-01-01",
    "end_date": "2022-07-23",
    "base_dir": "/home/tedy/passivbot5.4.2tedy/configs/live/PBSO/BT_UNIFORMISED/strat_d2692/",
    "ohlcv": true,
    "spot": false,
    "exchange": "bybit",
    "session_name": "2021-01-01_2022-07-23",
    "caches_dirpath": "/home/tedy/passivbot5.4.2tedy/configs/live/PBSO/BT_UNIFORMISED/strat_d2692/bybit/AVAXUSDT/caches/",
    "optimize_dirpath": "/home/tedy/passivbot5.4.2tedy/configs/live/PBSO/BT_UNIFORMISED/strat_d2692/bybit/AVAXUSDT/optimize/",
    "plots_dirpath": "/home/tedy/passivbot5.4.2tedy/configs/live/PBSO/BT_UNIFORMISED/strat_d2692/bybit/AVAXUSDT/plots/2022-07-31T020524/",
    "maker_fee": 0.0001,
    "taker_fee": 0.0006,
    "inverse": false,
    "max_leverage": 50,
    "min_qty": 0.1,
    "min_cost": 0.0,
    "qty_step": 0.1,
    "price_step": 0.005,
    "c_mult": 1.0,
    "hedge_mode": true,
    "n_parts": 0,
    "config_name": "neat_grid_0days",
    "logging_level": 0,
    "long": {
        "auto_unstuck_ema_dist": 0.024612266874332447,
        "auto_unstuck_wallet_exposure_threshold": 0.02033707126068811,
        "backwards_tp": true,
        "ema_span_0": 99.99216927772423,
        "ema_span_1": 68.81132631194242,
        "enabled": true,
        "eprice_exp_base": 1.3847516099072776,
        "eqty_exp_base": 1.9047997104734737,
        "grid_span": 0.2311454823679849,
        "initial_eprice_ema_dist": -0.07984793123539703,
        "initial_qty_pct": 0.01,
        "markup_range": 0.0015493281398301386,
        "max_n_entry_orders": 6,
        "min_markup": 0.0029255106975697703,
        "n_close_orders": 7,
        "wallet_exposure_limit": 0.5
    },
    "short": {
        "auto_unstuck_ema_dist": 0.09038368803174276,
        "auto_unstuck_wallet_exposure_threshold": 0.003952232919474736,
        "backwards_tp": true,
        "ema_span_0": 3015.9266115781315,
        "ema_span_1": 5251.0693296424615,
        "enabled": true,
        "eprice_exp_base": 1.1626929915669184,
        "eqty_exp_base": 1.6300663334317629,
        "grid_span": 0.2,
        "initial_eprice_ema_dist": -0.08918317588222421,
        "initial_qty_pct": 0.01,
        "markup_range": 0.0018832006390602477,
        "max_n_entry_orders": 9,
        "min_markup": 0.0027708683565569143,
        "n_close_orders": 12,
        "wallet_exposure_limit": 0.5
    },
    "n_days": 568.0,
    "passivbot_mode": "neat_grid",
    "result": {
        "DGstd_long": 0.019192040988111017,
        "DGstd_short": 0.05180512134176059,
        "adg_DGstd_ratio_long": 0.021245824499075,
        "adg_DGstd_ratio_short": -0.07518848775733,
        "adg_long": 0.0004077507346124606,
        "adg_per_exposure_long": 0.0008155014692249212,
        "adg_per_exposure_short": -0.016149869900009328,
        "adg_realized_long": 0.00022475126865950656,
        "adg_realized_per_exposure_long": 0.00044950253731901313,
        "adg_realized_per_exposure_short": -0.04805943529874113,
        "adg_realized_short": -0.024029717649370563,
        "adg_short": -0.008074934950004664,
        "avg_fills_per_day_long": 48.33462523138016,
        "avg_fills_per_day_short": 0.6126775544736758,
        "biggest_psize_long": 75.9,
        "biggest_psize_quote_long": 766.0529999999999,
        "biggest_psize_quote_short": 505.81463999999994,
        "biggest_psize_short": 124.8,
        "closest_bkr_long": 1.0,
        "closest_bkr_short": 0.0545205579765957,
        "eqbal_ratio_mean_long": 0.9500871887376392,
        "eqbal_ratio_mean_short": 0.9951629529812457,
        "eqbal_ratio_min_long": 0.7135157863611385,
        "eqbal_ratio_min_short": 0.09062118130292723,
        "equity_balance_ratio_mean_long": 0.9500871887376392,
        "equity_balance_ratio_mean_short": 0.9951629529812457,
        "equity_balance_ratio_std_long": 0.07743052490337535,
        "equity_balance_ratio_std_short": 0.04506668953389337,
        "exchange": "bybit",
        "fee_sum_long": -36.123634425000006,
        "fee_sum_short": -0.557907032,
        "final_balance_long": 1136.1485355749996,
        "final_balance_short": 0.001,
        "final_equity_long": 1135.7130355749996,
        "final_equity_short": 0.001,
        "gain_long": 0.17227217000000342,
        "gain_short": -0.92105482,
        "hrs_stuck_avg": 39.17231800766283,
        "hrs_stuck_avg_long": 0.5012673898388184,
        "hrs_stuck_avg_short": 39.17231800766283,
        "hrs_stuck_max": 13244.966666666667,
        "hrs_stuck_max_long": 191.8,
        "hrs_stuck_max_short": 13244.966666666667,
        "loss_sum_long": -688.0947398778751,
        "loss_sum_short": -932.8693600000001,
        "n_closes_long": 12430,
        "n_closes_short": 125,
        "n_days": 567.9986111111111,
        "n_entries_long": 15024,
        "n_entries_short": 222,
        "n_fills_long": 27454,
        "n_fills_short": 348,
        "n_ientries_long": 11699,
        "n_ientries_short": 125,
        "n_normal_closes_long": 11973,
        "n_normal_closes_short": 125,
        "n_rentries_long": 3198,
        "n_rentries_short": 97,
        "n_unstuck_closes_long": 457,
        "n_unstuck_closes_short": 0,
        "n_unstuck_entries_long": 127,
        "n_unstuck_entries_short": 0,
        "net_pnl_plus_fees_long": 136.14853557500342,
        "net_pnl_plus_fees_short": -921.6127270320001,
        "pa_distance_max_long": 1.3454123868961936,
        "pa_distance_max_short": 0.6451608866091046,
        "pa_distance_mean_long": 0.16809772068184237,
        "pa_distance_mean_short": 0.2552740785359463,
        "pa_distance_std_long": 0.26060236575132534,
        "pa_distance_std_short": 0.192876044126338,
        "pnl_sum_long": 172.27217000000343,
        "pnl_sum_short": -921.0548200000001,
        "profit_sum_long": 860.3669098778785,
        "profit_sum_short": 11.81454000000013,
        "starting_balance": 1000.0,
        "symbol": "AVAXUSDT",
        "volume_quote_long": 361236.3442500001,
        "volume_quote_short": 5073.25568
    }
}