{
    "market_type": "futures",
    "user": "bybit_pro",
    "symbol": "DOTUSDT",
    "latency_simulation_ms": 1000,
    "starting_balance": 1000.0,
    "start_date": "2021-01-01",
    "end_date": "2022-07-23",
    "base_dir": "/home/tedy/passivbot5.4.2tedy/configs/live/PBSO/BT_UNIFORMISED/strat_5986e/",
    "ohlcv": true,
    "spot": false,
    "exchange": "bybit",
    "session_name": "2021-01-01_2022-07-23",
    "caches_dirpath": "/home/tedy/passivbot5.4.2tedy/configs/live/PBSO/BT_UNIFORMISED/strat_5986e/bybit/DOTUSDT/caches/",
    "optimize_dirpath": "/home/tedy/passivbot5.4.2tedy/configs/live/PBSO/BT_UNIFORMISED/strat_5986e/bybit/DOTUSDT/optimize/",
    "plots_dirpath": "/home/tedy/passivbot5.4.2tedy/configs/live/PBSO/BT_UNIFORMISED/strat_5986e/bybit/DOTUSDT/plots/2022-07-31T050716/",
    "maker_fee": 0.0001,
    "taker_fee": 0.0006,
    "inverse": false,
    "max_leverage": 50,
    "min_qty": 0.1,
    "min_cost": 0.0,
    "qty_step": 0.1,
    "price_step": 0.005,
    "c_mult": 1.0,
    "hedge_mode": true,
    "n_parts": 0,
    "config_name": "neat_grid_0days",
    "logging_level": 0,
    "long": {
        "auto_unstuck_ema_dist": 0,
        "auto_unstuck_wallet_exposure_threshold": 0,
        "backwards_tp": true,
        "ema_span_0": 302.24962846175356,
        "ema_span_1": 299.2441445453312,
        "enabled": true,
        "eprice_exp_base": 1.0320828766385206,
        "eqty_exp_base": 2.895819790005283,
        "grid_span": 0.16881634839825507,
        "initial_eprice_ema_dist": -0.036539377630209605,
        "initial_qty_pct": 0.021836229727571807,
        "markup_range": 0.0042936018452949575,
        "max_n_entry_orders": 7,
        "min_markup": 0.002,
        "n_close_orders": 7,
        "wallet_exposure_limit": 0.9090909090909091
    },
    "short": {
        "auto_unstuck_ema_dist": 0,
        "auto_unstuck_wallet_exposure_threshold": 0,
        "backwards_tp": true,
        "ema_span_0": 1777.1442049140544,
        "ema_span_1": 2713.208433789674,
        "enabled": true,
        "eprice_exp_base": 1.1579387202733458,
        "eqty_exp_base": 2.19727139430921,
        "grid_span": 0.36607986735715825,
        "initial_eprice_ema_dist": -0.03285266405942448,
        "initial_qty_pct": 0.011697242111164116,
        "markup_range": 0.029737712123274012,
        "max_n_entry_orders": 6,
        "min_markup": 0.009571674581642075,
        "n_close_orders": 14,
        "wallet_exposure_limit": 0.09090909090909091
    },
    "n_days": 568.0,
    "passivbot_mode": "neat_grid",
    "result": {
        "DGstd_long": 0.024590485449326478,
        "DGstd_short": 0.01884404458309207,
        "adg_DGstd_ratio_long": 0.051462680899969394,
        "adg_DGstd_ratio_short": 0.0105132394212544,
        "adg_long": 0.001265492305854029,
        "adg_per_exposure_long": 0.0013920415364394318,
        "adg_per_exposure_short": 0.002179231476035229,
        "adg_realized_long": 0.001973370345214498,
        "adg_realized_per_exposure_long": 0.002170707379735948,
        "adg_realized_per_exposure_short": 0.0002548084952467278,
        "adg_realized_short": 2.3164408658793434e-05,
        "adg_short": 0.00019811195236683898,
        "avg_fills_per_day_long": 22.084561044016638,
        "avg_fills_per_day_short": 0.4154939737235273,
        "biggest_psize_long": 198.4,
        "biggest_psize_quote_long": 2785.9554000000003,
        "biggest_psize_quote_short": 91.258,
        "biggest_psize_short": 8.6,
        "closest_bkr_long": 1.0,
        "closest_bkr_short": 1.0,
        "eqbal_ratio_mean_long": 0.9466872341730603,
        "eqbal_ratio_mean_short": 0.88550060237862,
        "eqbal_ratio_min_long": 0.48206546777383646,
        "eqbal_ratio_min_short": 0.639583466174157,
        "equity_balance_ratio_mean_long": 0.9466872341730603,
        "equity_balance_ratio_mean_short": 0.88550060237862,
        "equity_balance_ratio_std_long": 0.1276943749691425,
        "equity_balance_ratio_std_short": 0.08970184525814999,
        "exchange": "bybit",
        "fee_sum_long": -70.14915471,
        "fee_sum_short": -0.07916362999999998,
        "final_balance_long": 3064.140545290005,
        "final_balance_short": 1013.2441363699992,
        "final_equity_long": 1723.5291452900046,
        "final_equity_short": 1013.2486363699992,
        "gain_long": 2.1342896999999996,
        "gain_short": 0.013323300000000022,
        "hrs_stuck_avg": 61.96348484848485,
        "hrs_stuck_avg_long": 1.110637662267123,
        "hrs_stuck_avg_short": 61.96348484848485,
        "hrs_stuck_max": 7018.616666666667,
        "hrs_stuck_max_long": 1826.0166666666667,
        "hrs_stuck_max_short": 7018.616666666667,
        "loss_sum_long": 0.0,
        "loss_sum_short": 0.0,
        "n_closes_long": 5457,
        "n_closes_short": 108,
        "n_days": 567.9986111111111,
        "n_entries_long": 7087,
        "n_entries_short": 128,
        "n_fills_long": 12544,
        "n_fills_short": 236,
        "n_ientries_long": 5119,
        "n_ientries_short": 74,
        "n_normal_closes_long": 5457,
        "n_normal_closes_short": 108,
        "n_rentries_long": 1968,
        "n_rentries_short": 54,
        "n_unstuck_closes_long": 0,
        "n_unstuck_closes_short": 0,
        "n_unstuck_entries_long": 0,
        "n_unstuck_entries_short": 0,
        "net_pnl_plus_fees_long": 2064.14054529,
        "net_pnl_plus_fees_short": 13.244136370000023,
        "pa_distance_max_long": 1.323699141368579,
        "pa_distance_max_short": 0.7995305101391349,
        "pa_distance_mean_long": 0.11421950660320813,
        "pa_distance_mean_short": 0.4720899782625993,
        "pa_distance_std_long": 0.2601865175462741,
        "pa_distance_std_short": 0.23541144708712214,
        "pnl_sum_long": 2134.2897,
        "pnl_sum_short": 13.323300000000023,
        "profit_sum_long": 2134.2897000000003,
        "profit_sum_short": 13.323300000000023,
        "starting_balance": 1000.0,
        "symbol": "DOTUSDT",
        "volume_quote_long": 701491.5471,
        "volume_quote_short": 791.6363
    }
}