{
    "market_type": "futures",
    "user": "bybit_pro",
    "symbol": "XRPUSDT",
    "latency_simulation_ms": 1000,
    "starting_balance": 1000.0,
    "start_date": "2021-01-01",
    "end_date": "2022-07-23",
    "base_dir": "/home/tedy/passivbot5.4.2tedy/configs/live/PBSO/BT_UNIFORMISED/strat_eb1ed/",
    "ohlcv": true,
    "spot": false,
    "exchange": "bybit",
    "session_name": "2021-01-01_2022-07-23",
    "caches_dirpath": "/home/tedy/passivbot5.4.2tedy/configs/live/PBSO/BT_UNIFORMISED/strat_eb1ed/bybit/XRPUSDT/caches/",
    "optimize_dirpath": "/home/tedy/passivbot5.4.2tedy/configs/live/PBSO/BT_UNIFORMISED/strat_eb1ed/bybit/XRPUSDT/optimize/",
    "plots_dirpath": "/home/tedy/passivbot5.4.2tedy/configs/live/PBSO/BT_UNIFORMISED/strat_eb1ed/bybit/XRPUSDT/plots/2022-07-31T030709/",
    "maker_fee": 0.0001,
    "taker_fee": 0.0006,
    "inverse": false,
    "max_leverage": 50,
    "min_qty": 1.0,
    "min_cost": 0.0,
    "qty_step": 1.0,
    "price_step": 0.0001,
    "c_mult": 1.0,
    "hedge_mode": true,
    "n_parts": 0,
    "config_name": "neat_grid_0days",
    "logging_level": 0,
    "long": {
        "auto_unstuck_ema_dist": 0.0023790855902760854,
        "auto_unstuck_wallet_exposure_threshold": 0.5886269116276958,
        "backwards_tp": true,
        "ema_span_0": 307.08907492214837,
        "ema_span_1": 348.7711661567338,
        "enabled": true,
        "eprice_exp_base": 1.2257371636124377,
        "eqty_exp_base": 1.5805814643357354,
        "grid_span": 0.20519765729947864,
        "initial_eprice_ema_dist": -0.09127249919659998,
        "initial_qty_pct": 0.01,
        "markup_range": 0.001527321025711749,
        "max_n_entry_orders": 7,
        "min_markup": 0.0029489612267636885,
        "n_close_orders": 12,
        "wallet_exposure_limit": 0.5
    },
    "short": {
        "auto_unstuck_ema_dist": 0.08284502287228132,
        "auto_unstuck_wallet_exposure_threshold": 0.4959671570301439,
        "backwards_tp": true,
        "ema_span_0": 2287.8198354315027,
        "ema_span_1": 2673.4221770730915,
        "enabled": true,
        "eprice_exp_base": 1,
        "eqty_exp_base": 1.5486316560535478,
        "grid_span": 0.5350613388577893,
        "initial_eprice_ema_dist": -0.07457841504307268,
        "initial_qty_pct": 0.01,
        "markup_range": 0.002,
        "max_n_entry_orders": 8,
        "min_markup": 0.0028868922149988614,
        "n_close_orders": 7,
        "wallet_exposure_limit": 0.5
    },
    "n_days": 568.0,
    "passivbot_mode": "neat_grid",
    "result": {
        "DGstd_long": 0.005043329044988525,
        "DGstd_short": 0.019949118882183606,
        "adg_DGstd_ratio_long": 0.17875651752850782,
        "adg_DGstd_ratio_short": -0.012654503629565089,
        "adg_long": 0.0009015279368325239,
        "adg_per_exposure_long": 0.0018030558736650479,
        "adg_per_exposure_short": -0.0005048923946024357,
        "adg_realized_long": 0.0008920446715834363,
        "adg_realized_per_exposure_long": 0.0017840893431668725,
        "adg_realized_per_exposure_short": -0.000939655032012654,
        "adg_realized_short": -0.000469827516006327,
        "adg_short": -0.0002524461973012179,
        "avg_fills_per_day_long": 51.09343479419697,
        "avg_fills_per_day_short": 10.728899474030404,
        "biggest_psize_long": 2800.0,
        "biggest_psize_quote_long": 835.5138,
        "biggest_psize_quote_short": 517.2660000000001,
        "biggest_psize_short": 1295.0,
        "closest_bkr_long": 1.0,
        "closest_bkr_short": 0.35805620371356095,
        "eqbal_ratio_mean_long": 0.9994533328697867,
        "eqbal_ratio_mean_short": 0.9953232221261682,
        "eqbal_ratio_min_long": 0.8385560911324457,
        "eqbal_ratio_min_short": 0.3955404154822043,
        "equity_balance_ratio_mean_long": 0.9994533328697867,
        "equity_balance_ratio_mean_short": 0.9953232221261682,
        "equity_balance_ratio_std_long": 0.0030118373734261345,
        "equity_balance_ratio_std_short": 0.03446805228032791,
        "exchange": "bybit",
        "fee_sum_long": -44.59190864,
        "fee_sum_short": -3.59040072,
        "final_balance_long": 1659.396991360012,
        "final_balance_short": 765.7311992800144,
        "final_equity_long": 1659.064291360012,
        "final_equity_short": 765.6431992800144,
        "gain_long": 0.7039889000000017,
        "gain_short": -0.23067839999999984,
        "hrs_stuck_avg": 2.250242104104765,
        "hrs_stuck_avg_long": 0.487343295676629,
        "hrs_stuck_avg_short": 2.250242104104765,
        "hrs_stuck_max": 189.63333333333333,
        "hrs_stuck_max_long": 56.78333333333333,
        "hrs_stuck_max_short": 189.63333333333333,
        "loss_sum_long": -348.8674914489334,
        "loss_sum_short": -319.94462885754666,
        "n_closes_long": 13150,
        "n_closes_short": 2904,
        "n_days": 567.9986111111111,
        "n_entries_long": 15871,
        "n_entries_short": 3190,
        "n_fills_long": 29021,
        "n_fills_short": 6094,
        "n_ientries_long": 11943,
        "n_ientries_short": 2858,
        "n_normal_closes_long": 13000,
        "n_normal_closes_short": 2899,
        "n_rentries_long": 3862,
        "n_rentries_short": 323,
        "n_unstuck_closes_long": 150,
        "n_unstuck_closes_short": 5,
        "n_unstuck_entries_long": 66,
        "n_unstuck_entries_short": 9,
        "net_pnl_plus_fees_long": 659.3969913600016,
        "net_pnl_plus_fees_short": -234.26880071999983,
        "pa_distance_max_long": 0.476961318391367,
        "pa_distance_max_short": 0.5471767123136259,
        "pa_distance_mean_long": 0.009524938737408785,
        "pa_distance_mean_short": 0.03618592302708029,
        "pa_distance_std_long": 0.010513860943155021,
        "pa_distance_std_short": 0.04508993106906382,
        "pnl_sum_long": 703.9889000000016,
        "pnl_sum_short": -230.67839999999984,
        "profit_sum_long": 1052.856391448935,
        "profit_sum_short": 89.26622885754685,
        "starting_balance": 1000.0,
        "symbol": "XRPUSDT",
        "volume_quote_long": 445919.08640000003,
        "volume_quote_short": 35904.00719999999
    }
}