{
    "market_type": "futures",
    "user": "bybit_pro",
    "symbol": "ADAUSDT",
    "latency_simulation_ms": 1000,
    "starting_balance": 1000.0,
    "start_date": "2021-01-01",
    "end_date": "2022-07-23",
    "base_dir": "/home/tedy/passivbot5.4.2tedy/configs/live/PBSO/BT_UNIFORMISED/strat_b3738/",
    "ohlcv": true,
    "spot": false,
    "exchange": "bybit",
    "session_name": "2021-01-01_2022-07-23",
    "caches_dirpath": "/home/tedy/passivbot5.4.2tedy/configs/live/PBSO/BT_UNIFORMISED/strat_b3738/bybit/ADAUSDT/caches/",
    "optimize_dirpath": "/home/tedy/passivbot5.4.2tedy/configs/live/PBSO/BT_UNIFORMISED/strat_b3738/bybit/ADAUSDT/optimize/",
    "plots_dirpath": "/home/tedy/passivbot5.4.2tedy/configs/live/PBSO/BT_UNIFORMISED/strat_b3738/bybit/ADAUSDT/plots/2022-07-31T091848/",
    "maker_fee": 0.0001,
    "taker_fee": 0.0006,
    "inverse": false,
    "max_leverage": 50,
    "min_qty": 1.0,
    "min_cost": 0.0,
    "qty_step": 1.0,
    "price_step": 0.0001,
    "c_mult": 1.0,
    "hedge_mode": true,
    "n_parts": 0,
    "config_name": "neat_grid_0days",
    "logging_level": 0,
    "long": {
        "auto_unstuck_ema_dist": 0,
        "auto_unstuck_wallet_exposure_threshold": 0,
        "backwards_tp": true,
        "ema_span_0": 893.7161626219206,
        "ema_span_1": 1424.1136068389035,
        "enabled": true,
        "eprice_exp_base": 1.0195698627666412,
        "eqty_exp_base": 2.1597400061766843,
        "grid_span": 0.1401160593629256,
        "initial_eprice_ema_dist": -0.07379161801495641,
        "initial_qty_pct": 0.013911409913558818,
        "markup_range": 0.002727230516984998,
        "max_n_entry_orders": 8,
        "min_markup": 0.002,
        "n_close_orders": 9,
        "wallet_exposure_limit": 0.9090909090909091
    },
    "short": {
        "auto_unstuck_ema_dist": 0,
        "auto_unstuck_wallet_exposure_threshold": 0,
        "backwards_tp": true,
        "ema_span_0": 2564.0978080309205,
        "ema_span_1": 7278.764102408051,
        "enabled": true,
        "eprice_exp_base": 2.575207598052669,
        "eqty_exp_base": 2.6816849363818043,
        "grid_span": 0.339940350781226,
        "initial_eprice_ema_dist": -0.06798408644789519,
        "initial_qty_pct": 0.03241724560841256,
        "markup_range": 0.01804831711126957,
        "max_n_entry_orders": 16,
        "min_markup": 0.00975445289515463,
        "n_close_orders": 20,
        "wallet_exposure_limit": 0.09090909090909091
    },
    "n_days": 568.0,
    "passivbot_mode": "neat_grid",
    "result": {
        "DGstd_long": 0.01452127600083655,
        "DGstd_short": 0.03685180612460302,
        "adg_DGstd_ratio_long": 0.13898038325477996,
        "adg_DGstd_ratio_short": 0.01787292876752185,
        "adg_long": 0.002018172503944702,
        "adg_per_exposure_long": 0.002219989754339172,
        "adg_per_exposure_short": 0.007245146764015108,
        "adg_realized_long": 0.0019167781527291705,
        "adg_realized_per_exposure_long": 0.0021084559680020877,
        "adg_realized_per_exposure_short": 0.0003929603978387597,
        "adg_realized_short": 3.5723672530796335e-05,
        "adg_short": 0.0006586497058195553,
        "avg_fills_per_day_long": 39.040588420844145,
        "avg_fills_per_day_short": 0.8221851090207086,
        "biggest_psize_long": 6456.0,
        "biggest_psize_quote_long": 2664.7354,
        "biggest_psize_quote_short": 92.43180000000002,
        "biggest_psize_short": 302.0,
        "closest_bkr_long": 1.0,
        "closest_bkr_short": 0.373743048481504,
        "eqbal_ratio_mean_long": 0.9948311511276795,
        "eqbal_ratio_mean_short": 0.7669689034581989,
        "eqbal_ratio_min_long": 0.5927076829777723,
        "eqbal_ratio_min_short": 0.2967038851815696,
        "equity_balance_ratio_mean_long": 0.9948311511276795,
        "equity_balance_ratio_mean_short": 0.7669689034581989,
        "equity_balance_ratio_std_long": 0.02447216487407903,
        "equity_balance_ratio_std_short": 0.15545998951237003,
        "exchange": "bybit",
        "fee_sum_long": -84.182109018,
        "fee_sum_short": -0.18402173100000002,
        "final_balance_long": 2967.39729098195,
        "final_balance_short": 1020.4978882689995,
        "final_equity_long": 2963.25929098195,
        "final_equity_short": 986.9971882689996,
        "gain_long": 2.051579400000003,
        "gain_short": 0.02068190999999998,
        "hrs_stuck_avg": 59.26942028985507,
        "hrs_stuck_avg_long": 0.6315774030145787,
        "hrs_stuck_avg_short": 59.26942028985507,
        "hrs_stuck_max": 12865.516666666666,
        "hrs_stuck_max_long": 436.3666666666667,
        "hrs_stuck_max_short": 12865.516666666666,
        "loss_sum_long": 0.0,
        "loss_sum_short": 0.0,
        "n_closes_long": 9554,
        "n_closes_short": 195,
        "n_days": 567.9986111111111,
        "n_entries_long": 12621,
        "n_entries_short": 272,
        "n_fills_long": 22175,
        "n_fills_short": 467,
        "n_ientries_long": 8945,
        "n_ientries_short": 20,
        "n_normal_closes_long": 9554,
        "n_normal_closes_short": 195,
        "n_rentries_long": 3676,
        "n_rentries_short": 252,
        "n_unstuck_closes_long": 0,
        "n_unstuck_closes_short": 0,
        "n_unstuck_entries_long": 0,
        "n_unstuck_entries_short": 0,
        "net_pnl_plus_fees_long": 1967.3972909820031,
        "net_pnl_plus_fees_short": 20.49788826899998,
        "pa_distance_max_long": 0.8112821097511105,
        "pa_distance_max_short": 0.8859069498755777,
        "pa_distance_mean_long": 0.01609468766229283,
        "pa_distance_mean_short": 0.6378466303934683,
        "pa_distance_std_long": 0.031962282155578135,
        "pa_distance_std_short": 0.2110108359222272,
        "pnl_sum_long": 2051.5794000000033,
        "pnl_sum_short": 20.68190999999998,
        "profit_sum_long": 2051.5794000000033,
        "profit_sum_short": 20.68190999999998,
        "starting_balance": 1000.0,
        "symbol": "ADAUSDT",
        "volume_quote_long": 841821.0901799999,
        "volume_quote_short": 1840.21731
    }
}